agsadmin/RestAdmin.py
agsadmin/SharingAdmin.py
agsadmin/__init__.py
agsadmin/_admin_base.py
agsadmin/_auth.py
agsadmin/_endpoint_base.py
agsadmin/_utils.py
agsadmin/_version.py
agsadmin/exceptions/__init__.py
agsadmin/exceptions/ags_admin_error.py
agsadmin/exceptions/authentication_error.py
agsadmin/exceptions/communication_error.py
agsadmin/exceptions/invalid_service_type_error.py
agsadmin/exceptions/unknown_service_error.py
agsadmin/rest_admin/__init__.py
agsadmin/rest_admin/machines/Machine.py
agsadmin/rest_admin/machines/Machines.py
agsadmin/rest_admin/machines/__init__.py
agsadmin/rest_admin/services/FeatureServer.py
agsadmin/rest_admin/services/Folder.py
agsadmin/rest_admin/services/GeoDataServer.py
agsadmin/rest_admin/services/GeocodeServer.py
agsadmin/rest_admin/services/GeometryServer.py
agsadmin/rest_admin/services/GlobeServer.py
agsadmin/rest_admin/services/GpServer.py
agsadmin/rest_admin/services/ImageServer.py
agsadmin/rest_admin/services/MapServer.py
agsadmin/rest_admin/services/SearchServer.py
agsadmin/rest_admin/services/Service.py
agsadmin/rest_admin/services/ServiceType.py
agsadmin/rest_admin/services/Services.py
agsadmin/rest_admin/services/VectorTileServer.py
agsadmin/rest_admin/services/WorkspaceServer.py
agsadmin/rest_admin/services/__init__.py
agsadmin/rest_admin/services/_folder_mixin.py
agsadmin/rest_admin/services/_permissions_mixin.py
agsadmin/rest_admin/services/_service_factory.py
agsadmin/rest_admin/services/types/Types.py
agsadmin/rest_admin/services/types/__init__.py
agsadmin/rest_admin/services/types/extensions/Extensions.py
agsadmin/rest_admin/services/types/extensions/__init__.py
agsadmin/rest_admin/system/Directories.py
agsadmin/rest_admin/system/Directory.py
agsadmin/rest_admin/system/System.py
agsadmin/rest_admin/system/__init__.py
agsadmin/rest_admin/system/handlers/Handlers.py
agsadmin/rest_admin/system/handlers/__init__.py
agsadmin/rest_admin/system/handlers/rest/Cache.py
agsadmin/rest_admin/system/handlers/rest/Rest.py
agsadmin-0.5.3.dist-info/LICENSE
agsadmin-0.5.3.dist-info/METADATA
agsadmin-0.5.3.dist-info/WHEEL
agsadmin-0.5.3.dist-info/top_level.txt
agsadmin-0.5.3.dist-info/RECORD
