Metadata-Version: 2.1
Name: agsadmin
Version: 0.5.3
Summary: ArcGIS Server REST Admin API Proxy
Home-page: https://github.com/DavidWhittingham/agsadmin
Author: David Whittingham; Adam Kerz; Daniel Baternik
License: BSD 3-Clause
Keywords: arcgis esri
Classifier: Development Status :: 4 - Beta
Classifier: Intended Audience :: Developers
Classifier: Natural Language :: English
Classifier: License :: OSI Approved :: BSD License
Classifier: Programming Language :: Python
License-File: LICENSE
Requires-Dist: enum34 >=1.1.6
Requires-Dist: future >=0.16.0
Requires-Dist: python-dateutil >=2.5.3
Requires-Dist: requests-toolbelt <1.1,>=1.0.0
Requires-Dist: rsa <=4.0,>=3.1.1 ; python_version < "3"
Requires-Dist: requests <2.28.0,>=2.3.0 ; python_version < "3"
Requires-Dist: rsa >=4.7 ; python_version >= "3"
Requires-Dist: requests >=2.3.0 ; python_version >= "3"
